gspWeb/__init__.py
gspWeb/econometrics/__init__.py
gspWeb/econometrics/olsModel.py
gspWeb-0.1.0.dist-info/LICENSE.txt
gspWeb-0.1.0.dist-info/METADATA
gspWeb-0.1.0.dist-info/WHEEL
gspWeb-0.1.0.dist-info/top_level.txt
gspWeb-0.1.0.dist-info/RECORD
