Metadata-Version: 2.1
Name: gspWeb
Version: 0.1.0
Summary: Fitting ols model in python
Home-page: 
Author: Geofrey Wanyama
Author-email: wanyamag17@gmail.com
License-File: LICENSE.txt
Requires-Dist: matplotlib
Requires-Dist: numpy
Requires-Dist: pandas
Requires-Dist: plotly (==5.14.0)
Requires-Dist: scipy
Requires-Dist: seaborn
Requires-Dist: statsmodels (==0.13.5)
